causalmodels/__init__.py
causalmodels/exception.py
causalmodels/interface.py
causalmodels/lingam.py
causalmodels/result.py
causalmodels-0.4.0.dist-info/DESCRIPTION.rst
causalmodels-0.4.0.dist-info/METADATA
causalmodels-0.4.0.dist-info/RECORD
causalmodels-0.4.0.dist-info/WHEEL
causalmodels-0.4.0.dist-info/metadata.json
causalmodels-0.4.0.dist-info/top_level.txt
