Metadata-Version: 2.0
Name: causalmodels
Version: 0.4.0
Summary: Causal models in Python
Home-page: http://github.com/roronya/causalmodels
Author: roronya
Author-email: roronya628@gmail.com
License: MIT
Keywords: causality machine	learning causalmodels
Platform: UNKNOWN
Classifier: Development Status :: 4 - Beta
Classifier: Intended Audience :: Science/Research
Classifier: License :: OSI Approved :: MIT License
Classifier: Programming Language :: Python :: 3
Classifier: Topic :: Scientific/Engineering :: Mathematics
Requires-Dist: graphviz
Requires-Dist: numpy
Requires-Dist: scikit-learn
Requires-Dist: scipy
Requires-Dist: tqdm
